kabaddiPy/__init__.py
kabaddiPy/kabaddiPy.py
kabaddiPy/MatchData_pbp/Season_PKL_Season_10_2023/100_Match_100_ID_3128.json
kabaddiPy/MatchData_pbp/Season_PKL_Season_10_2023/101_Match_101_ID_3129.json
kabaddiPy/MatchData_pbp/Season_PKL_Season_10_2023/102_Match_102_ID_3130.json
kabaddiPy/MatchData_pbp/Season_PKL_Season_10_2023/103_Match_103_ID_3131.json
kabaddiPy/MatchData_pbp/Season_PKL_Season_10_2023/104_Match_104_ID_3132.json
kabaddiPy/MatchData_pbp/Season_PKL_Season_10_2023/105_Match_105_ID_3133.json
kabaddiPy/MatchData_pbp/Season_PKL_Season_10_2023/106_Match_106_ID_3134.json
kabaddiPy/MatchData_pbp/Season_PKL_Season_10_2023/107_Match_107_ID_3135.json
kabaddiPy/MatchData_pbp/Season_PKL_Season_10_2023/108_Match_108_ID_3136.json
kabaddiPy/MatchData_pbp/Season_PKL_Season_10_2023/109_Match_109_ID_3137.json
kabaddiPy/MatchData_pbp/Season_PKL_Season_10_2023/10_Match_10_ID_3038.json
kabaddiPy/MatchData_pbp/Season_PKL_Season_10_2023/110_Match_110_ID_3138.json
kabaddiPy/MatchData_pbp/Season_PKL_Season_10_2023/111_Match_111_ID_3139.json
kabaddiPy/MatchData_pbp/Season_PKL_Season_10_2023/112_Match_112_ID_3140.json
kabaddiPy/MatchData_pbp/Season_PKL_Season_10_2023/113_Match_113_ID_3141.json
kabaddiPy/MatchData_pbp/Season_PKL_Season_10_2023/114_Match_114_ID_3142.json
kabaddiPy/MatchData_pbp/Season_PKL_Season_10_2023/115_Match_115_ID_3143.json
kabaddiPy/MatchData_pbp/Season_PKL_Season_10_2023/116_Match_116_ID_3144.json
kabaddiPy/MatchData_pbp/Season_PKL_Season_10_2023/117_Match_117_ID_3145.json
kabaddiPy/MatchData_pbp/Season_PKL_Season_10_2023/118_Match_118_ID_3146.json
kabaddiPy/MatchData_pbp/Season_PKL_Season_10_2023/119_Match_119_ID_3147.json
kabaddiPy/MatchData_pbp/Season_PKL_Season_10_2023/11_Match_11_ID_3039.json
kabaddiPy/MatchData_pbp/Season_PKL_Season_10_2023/120_Match_120_ID_3148.json
kabaddiPy/MatchData_pbp/Season_PKL_Season_10_2023/121_Match_121_ID_3149.json
kabaddiPy/MatchData_pbp/Season_PKL_Season_10_2023/122_Match_122_ID_3150.json
kabbaddiPy-0.0.3.dist-info/LICENSE
kabbaddiPy-0.0.3.dist-info/METADATA
kabbaddiPy-0.0.3.dist-info/WHEEL
kabbaddiPy-0.0.3.dist-info/top_level.txt
kabbaddiPy-0.0.3.dist-info/RECORD
