Metadata-Version: 2.1
Name: kabbaddiPy
Version: 0.0.3
Summary: A Python module for aggregating Kabaddi data
Home-page: https://github.com/kabaddiPy/kabaddiPy
Author: Aniruddha Mukherjee, Bhaskar Lalwani
Author-email: Aniruddha Mukherjee <mukh.aniruddha@gmail.com>, Bhaskar Lalwani <bhaskarlalwani2040@gmail.com>
License: GNU GENERAL PUBLIC LICENSE
Project-URL: Homepage, https://github.com/kabaddiPy/kabaddiPy
Project-URL: Bug Tracker, https://github.com/kabaddiPy/kabaddiPy
Project-URL: Docs, https://kabaddipy.github.io/kabaddiPy/
Keywords: kabaddi,open-source,aggregator,sports-analysis
Classifier: Development Status :: 3 - Alpha
Classifier: Intended Audience :: Developers
Classifier: License :: OSI Approved :: GNU General Public License v2 (GPLv2)
Classifier: Operating System :: OS Independent
Classifier: Programming Language :: Python :: 3
Classifier: Programming Language :: Python :: 3.7
Classifier: Programming Language :: Python :: 3.8
Classifier: Programming Language :: Python :: 3.9
Classifier: Programming Language :: Python :: 3.10
Requires-Python: >=3.7
License-File: LICENSE
Requires-Dist: pandas
Requires-Dist: matplotlib
Requires-Dist: seaborn
Requires-Dist: jinja2
